retro_bip_utils/P2PKH.py
retro_bip_utils/P2SH.py
retro_bip_utils/P2WPKH.py
retro_bip_utils/__init__.py
retro_bip_utils/_version.py
retro_bip_utils/base58.py
retro_bip_utils/base58_ex.py
retro_bip_utils/bech32.py
retro_bip_utils/bech32_ex.py
retro_bip_utils/bip32.py
retro_bip_utils/bip32_ex.py
retro_bip_utils/bip32_key_ser.py
retro_bip_utils/bip32_path.py
retro_bip_utils/bip32_utils.py
retro_bip_utils/bip39.py
retro_bip_utils/bip39_ex.py
retro_bip_utils/bip39_wordslist_en.txt
retro_bip_utils/bip44.py
retro_bip_utils/bip44_base.py
retro_bip_utils/bip44_base_ex.py
retro_bip_utils/bip44_coins.py
retro_bip_utils/bip49.py
retro_bip_utils/bip49_coins.py
retro_bip_utils/bip84.py
retro_bip_utils/bip84_coins.py
retro_bip_utils/bip_coin_base.py
retro_bip_utils/bip_coin_conf.py
retro_bip_utils/bip_coin_conf_helper.py
retro_bip_utils/bip_keys.py
retro_bip_utils/eth_addr.py
retro_bip_utils/key_helper.py
retro_bip_utils/utils.py
retro_bip_utils/wif.py
retro_bip_utils/xrp_addr.py
retro_bip_utils-1.0.5.dist-info/LICENSE
retro_bip_utils-1.0.5.dist-info/METADATA
retro_bip_utils-1.0.5.dist-info/WHEEL
retro_bip_utils-1.0.5.dist-info/top_level.txt
retro_bip_utils-1.0.5.dist-info/RECORD
