Metadata-Version: 2.1
Name: retro-bip-utils
Version: 1.0.5
Summary: Implementation of BIP39, BIP32, BIP44, BIP49 and BIP84 for wallet seeds, keys and addresses generation. Supported coins: Bitcoin, Litecoin, Dogecoin, Ethereum.
Home-page: https://github.com/laalaguer/retro_bip_utils
Author: Emanuele Bellocchia, A Byte Ahead
Author-email: laalaguer@gmail.com
Maintainer: Emanuele Bellocchia, A Byte Ahead
Maintainer-email: laalaguer@gmail.com
License: MIT
Download-URL: https://github.com/laalaguer/retro_bip_utils/archive/v1.0.5.tar.gz
Keywords: bitcoin,litecoin,dogecoin,dash,ethereum,ripple,wallet,hd-wallet,bip39,bip32,bip44,bip49,bip84,python
Platform: any
Classifier: Programming Language :: Python :: 3
Classifier: License :: OSI Approved :: MIT License
Classifier: Operating System :: OS Independent
Classifier: Intended Audience :: Developers
Requires-Python: >=3.6
License-File: LICENSE
Requires-Dist: ecdsa
Requires-Dist: eth-hash
